{
  "config": {
    "step": {
      "user": {
        "title": "Kstar Solar Inverter Configuration",
        "description": "Please enter your Kstar Solar Inverter configuration. Get the encrypted password from the passWord field in your browser cookies.",
        "data": {
          "host": "Backend URL",
          "station_id": "Station ID",
          "username": "Username",
          "password": "Password (encrypted)"
        }
      }
    },
    "error": {
      "cannot_connect": "Failed to connect to Kstar Solar Inverter",
      "invalid_auth": "Authentication failed",
      "unknown": "Unknown error"
    },
    "abort": {
      "already_configured": "Device is already configured"
    }
  }
}
